th_company_info/__init__.py
th_company_info/exception.py
th_company_info/scraper.py
th_company_info-0.0.1.dist-info/LICENSE
th_company_info-0.0.1.dist-info/METADATA
th_company_info-0.0.1.dist-info/WHEEL
th_company_info-0.0.1.dist-info/top_level.txt
th_company_info-0.0.1.dist-info/RECORD
