Metadata-Version: 2.1
Name: th-company-info
Version: 0.0.1
Summary: A Python library to get a company information from dataforthai.com (For my eductaional purpose)
Author: Grassroot Engineer
Author-email: q_electronics@hotmail.com
Classifier: Programming Language :: Python :: 3
Classifier: License :: OSI Approved :: MIT License
Classifier: Operating System :: OS Independent
Requires-Python: >=3.6
License-File: LICENSE
Requires-Dist: cloudscraper
Requires-Dist: beautifulsoup4
